neon_sftp/__init__.py
neon_sftp/connector.py
neon_sftp-0.0.2a1.dist-info/METADATA
neon_sftp-0.0.2a1.dist-info/WHEEL
neon_sftp-0.0.2a1.dist-info/top_level.txt
neon_sftp-0.0.2a1.dist-info/zip-safe
neon_sftp-0.0.2a1.dist-info/RECORD
